LICENSE.txt
MANIFEST.in
README.rst
setup.py
rpc_exceptions/__init__.py
rpc_exceptions/base_exceptions.py
rpc_exceptions/exception_handler.py
rpc_exceptions.egg-info/PKG-INFO
rpc_exceptions.egg-info/SOURCES.txt
rpc_exceptions.egg-info/dependency_links.txt
rpc_exceptions.egg-info/top_level.txt