Metadata-Version: 1.0
Name: rpc-exceptions
Version: 0.1
Summary: RPC Exceptions
Home-page: https://github.com/axialmarket/rpc_exceptions
Author: Jeff Rand
Author-email: jeff.rand@axial.net
License: 3-BSD
Platform: UNKNOWN
